dirac_wallet/__init__.py
dirac_wallet/cli/__init__.py
dirac_wallet/cli/commands.py
dirac_wallet/core/__init__.py
dirac_wallet/core/address.py
dirac_wallet/core/keys.py
dirac_wallet/core/secure_storage.py
dirac_wallet/core/storage.py
dirac_wallet/core/transactions.py
dirac_wallet/core/wallet.py
dirac_wallet/network/__init__.py
dirac_wallet/network/solana_client.py
dirac_wallet/utils/__init__.py
dirac_wallet/utils/logger.py
dirac_wallet/utils/security_validator.py
dirac_wallet-0.1.3.dist-info/METADATA
dirac_wallet-0.1.3.dist-info/WHEEL
dirac_wallet-0.1.3.dist-info/entry_points.txt
dirac_wallet-0.1.3.dist-info/top_level.txt
dirac_wallet-0.1.3.dist-info/RECORD
