Metadata-Version: 2.4
Name: dirac-wallet
Version: 0.1.3
Summary: Quantum-resistant Solana wallet
Home-page: https://github.com/mk0dz/dirac-wallet
Author: Dirac Labs
Author-email: Dirac Labs <Mukulkumar2027@gmail.com>
License: MIT
Project-URL: Homepage, https://github.com/mk0dz/dirac-wallet
Project-URL: Bug Reports, https://github.com/mk0dz/dirac-wallet/issues
Project-URL: Source, https://github.com/mk0dz/dirac-wallet
Project-URL: Documentation, https://crypto.dirac.fun
Keywords: solana,blockchain,cryptocurrency,quantum,wallet,post-quantum,cryptography
Classifier: Programming Language :: Python :: 3
Classifier: Programming Language :: Python :: 3.8
Classifier: Programming Language :: Python :: 3.9
Classifier: Programming Language :: Python :: 3.10
Classifier: License :: OSI Approved :: MIT License
Classifier: Operating System :: OS Independent
Classifier: Topic :: Security :: Cryptography
Classifier: Topic :: Software Development :: Libraries :: Python Modules
Classifier: Topic :: Office/Business :: Financial
Classifier: Intended Audience :: Developers
Classifier: Intended Audience :: Financial and Insurance Industry
Classifier: Development Status :: 4 - Beta
Requires-Python: >=3.8
Requires-Dist: solana>=0.25.0
Requires-Dist: solders>=0.26.0
Requires-Dist: click>=8.0.0
Requires-Dist: pyyaml>=6.0
Requires-Dist: pycryptodome>=3.17.0
Requires-Dist: python-dotenv>=1.0.0
Requires-Dist: base58>=2.1.0
Requires-Dist: aiohttp>=3.8.0
Requires-Dist: asyncio>=3.4.3
Requires-Dist: rich>=13.0.0
Requires-Dist: cryptography>=41.0.0
Requires-Dist: psutil>=5.9.0
Requires-Dist: matplotlib>=3.5.0
Requires-Dist: numpy>=1.20.0
Requires-Dist: dirac-hashes
Dynamic: author
Dynamic: home-page
Dynamic: requires-python
